setup.py
distributions_udacity_dsnd_chp03lesson04_5_exercise_upload_to_pypi/Binomialdistribution.py
distributions_udacity_dsnd_chp03lesson04_5_exercise_upload_to_pypi/Gaussiandistribution.py
distributions_udacity_dsnd_chp03lesson04_5_exercise_upload_to_pypi/Generaldistribution.py
distributions_udacity_dsnd_chp03lesson04_5_exercise_upload_to_pypi/__init__.py
distributions_udacity_dsnd_chp03lesson04_5_exercise_upload_to_pypi.egg-info/PKG-INFO
distributions_udacity_dsnd_chp03lesson04_5_exercise_upload_to_pypi.egg-info/SOURCES.txt
distributions_udacity_dsnd_chp03lesson04_5_exercise_upload_to_pypi.egg-info/dependency_links.txt
distributions_udacity_dsnd_chp03lesson04_5_exercise_upload_to_pypi.egg-info/not-zip-safe
distributions_udacity_dsnd_chp03lesson04_5_exercise_upload_to_pypi.egg-info/top_level.txt