Metadata-Version: 1.0
Name: distributions-udacity-dsnd-chp03lesson04-5-exercise-upload-to-pypi
Version: 0.1
Summary: Gaussian distributions
Home-page: UNKNOWN
Author: UNKNOWN
Author-email: UNKNOWN
License: UNKNOWN
Platform: UNKNOWN
